twisted/plugins/onion_service_endpoint_dropin.py
txxonion-0.1.dist-info/DESCRIPTION.rst
txxonion-0.1.dist-info/METADATA
txxonion-0.1.dist-info/RECORD
txxonion-0.1.dist-info/WHEEL
txxonion-0.1.dist-info/metadata.json
txxonion-0.1.dist-info/top_level.txt
